files/__init__.py
files/admin.py
files/apps.py
files/conf.py
files/exceptions.py
files/helpers.py
files/utils.py
files/api/__init__.py
files/api/urls.py
files/api/serializers/__init__.py
files/api/serializers/uploaded_file.py
files/api/serializers/uploaded_file_reverse.py
files/api/serializers/uploaded_file_version.py
files/api/serializers/user.py
files/api/views/__init__.py
files/api/views/uploaded_file.py
files/api/views/uploaded_file_mixin.py
files/faker_factories/__init__.py
files/faker_factories/uploaded_file.py
files/migrations/0001_initial.py
files/migrations/0002_uploadedfilevisibility.py
files/migrations/__init__.py
files/mixins/__init__.py
files/mixins/uploaded_file_mixin.py
files/models/__init__.py
files/models/uploaded_file.py
files/models/uploaded_file_permission_mixin.py
files/models/uploaded_file_version.py
files/models/uploaded_file_visibility.py
files/signals/__init__.py
files/signals/uploaded_file.py
files/urls/__init__.py
files/views/__init__.py
files/views/uploaded_file.py
django_filestack-0.4.2.dist-info/AUTHORS.rst
django_filestack-0.4.2.dist-info/LICENSE
django_filestack-0.4.2.dist-info/METADATA
django_filestack-0.4.2.dist-info/WHEEL
django_filestack-0.4.2.dist-info/top_level.txt
django_filestack-0.4.2.dist-info/RECORD
