Metadata-Version: 2.1
Name: django-filestack
Version: 0.4.2
Summary: Add Model support for Filestack files
Home-page: https://github.com/exolever/django-filestack
Author: Tomas
Author-email: tomas@openexo.com
License: BSD
Keywords: django-filestack
Platform: UNKNOWN
Classifier: Development Status :: 3 - Alpha
Classifier: Framework :: Django :: 1.11
Classifier: Framework :: Django :: 2.0
Classifier: Intended Audience :: Developers
Classifier: License :: OSI Approved :: BSD License
Classifier: Natural Language :: English
Classifier: Programming Language :: Python :: 2
Classifier: Programming Language :: Python :: 2.7
Classifier: Programming Language :: Python :: 3
Classifier: Programming Language :: Python :: 3.4
Classifier: Programming Language :: Python :: 3.5
Classifier: Programming Language :: Python :: 3.6
